{
	"animations": [
		{
			"loop": false,
			"offsets": [
				-3,
				0
			],
			"fps": 24,
			"anim": "idle",
			"indices": [],
			"name": "Idle"
		},
		{
			"loop": false,
			"offsets": [
				8,
				23
			],
			"fps": 24,
			"anim": "singUP",
			"indices": [],
			"name": "Up"
		},
		{
			"loop": false,
			"offsets": [
				62,
				0
			],
			"fps": 24,
			"anim": "singLEFT",
			"indices": [],
			"name": "Left"
		},
		{
			"loop": false,
			"offsets": [
				-27,
				1
			],
			"fps": 24,
			"anim": "singRIGHT",
			"indices": [],
			"name": "Right"
		},
		{
			"loop": false,
			"offsets": [
				-28,
				-62
			],
			"fps": 24,
			"anim": "singDOWN",
			"indices": [],
			"name": "Down"
		},
		{
			"loop": false,
			"offsets": [
				-2,
				1
			],
			"fps": 24,
			"anim": "hey",
			"indices": [],
			"name": "Hey"
		}
	],
	"no_antialiasing": false,
	"image": "characters/NKO_BF",
	"position": [
		-50,
		215
	],
	"healthicon": "bf",
	"flip_x": false,
	"healthbar_colors": [
		48,
		176,
		209
	],
	"camera_position": [
		100,
		100
	],
	"sing_duration": 4,
	"scale": 0.6
}